ast_nodes.py
interpreter.py
lexer.py
parser.py
when.py
when_lang-0.5.0.dist-info/licenses/LICENSE
when_lang-0.5.0.dist-info/METADATA
when_lang-0.5.0.dist-info/WHEEL
when_lang-0.5.0.dist-info/entry_points.txt
when_lang-0.5.0.dist-info/top_level.txt
when_lang-0.5.0.dist-info/RECORD
